setup.cfg
setup.py
lios/__init__.py
lios/cli.py
lios.egg-info/PKG-INFO
lios.egg-info/SOURCES.txt
lios.egg-info/dependency_links.txt
lios.egg-info/entry_points.txt
lios.egg-info/not-zip-safe
lios.egg-info/requires.txt
lios.egg-info/top_level.txt