Metadata-Version: 1.1
Name: lios
Version: 0.1.0
Summary: Auto sync photos/videos/music/files between iOS & Linux.
Home-page: https://github.com/chillaranand/lios
Author: anand reddy pandikunta
Author-email: anand21nanda@gmail.com
License: BSD
Platform: any
Classifier: Development Status :: 4 - Beta
Classifier: Environment :: Console
Classifier: Intended Audience :: Developers
Classifier: License :: OSI Approved :: BSD License
Classifier: Operating System :: POSIX
Classifier: Operating System :: MacOS
Classifier: Operating System :: Unix
Classifier: Programming Language :: Python
Classifier: Programming Language :: Python :: 2
Classifier: Topic :: Software Development :: Libraries :: Python Modules
